zeppelin/utils/__init__.py
zeppelin/utils/service_config.py
zeppelin/utils/service_config_test.py
zeppelin_utils-0.0.1.dist-info/WHEEL
zeppelin_utils-0.0.1.dist-info/METADATA
zeppelin_utils-0.0.1.dist-info/RECORD
