Metadata-Version: 2.1
Name: zeppelin-utils
Version: 0.0.1
Summary: Package with util functions for zeppelin
Author: ArcLight_Slavik
Requires-Python: >=3.7,<4.0
Classifier: Programming Language :: Python :: 3
Classifier: Programming Language :: Python :: 3.7
Classifier: Programming Language :: Python :: 3.8
Classifier: Programming Language :: Python :: 3.9
